quicklz.so
pyquicklz-1.4.1.dist-info/top_level.txt
pyquicklz-1.4.1.dist-info/DESCRIPTION.rst
pyquicklz-1.4.1.dist-info/RECORD
pyquicklz-1.4.1.dist-info/metadata.json
pyquicklz-1.4.1.dist-info/WHEEL
pyquicklz-1.4.1.dist-info/METADATA
