Metadata-Version: 1.0
Name: pyquicklz
Version: 1.4.1
Summary: python binding of quicklz
Home-page: UNKNOWN
Author: UNKNOWN
Author-email: UNKNOWN
License: UNKNOWN
Platform: UNKNOWN
